psychopy_catppuccin/__init__.py
psychopy_catppuccin/themes/__init__.py
psychopy_catppuccin/themes/catppuccin_latte.py
psychopy_catppuccin-0.0.1.dist-info/METADATA
psychopy_catppuccin-0.0.1.dist-info/WHEEL
psychopy_catppuccin-0.0.1.dist-info/entry_points.txt
psychopy_catppuccin-0.0.1.dist-info/top_level.txt
psychopy_catppuccin-0.0.1.dist-info/RECORD
